LICENSE
MANIFEST.in
README.md
requirements.txt
setup.py
squirrel_api/__init__.py
squirrel_api/api.py
squirrel_api/exceptions.py
squirrelapi.egg-info/PKG-INFO
squirrelapi.egg-info/SOURCES.txt
squirrelapi.egg-info/dependency_links.txt
squirrelapi.egg-info/requires.txt
squirrelapi.egg-info/top_level.txt