Metadata-Version: 1.1
Name: squirrelapi
Version: 0.6.1
Summary: Python wrapper for C3 Squirrel Voicemail HTTP API
Home-page: https://github.com/ox-it/python-squirrelapi
Author: Mobile Oxford
Author-email: mobileoxford@oucs.ox.ac.uk
License: UNKNOWN
Platform: UNKNOWN
Classifier: Development Status :: 4 - Beta
Classifier: License :: OSI Approved :: Apache Software License
Classifier: Intended Audience :: Developers
Classifier: Operating System :: OS Independent
Classifier: Programming Language :: Python
Classifier: Topic :: Communications :: Telephony
Classifier: Topic :: Communications :: Internet Phone
